mcoauth/__init__.py
mcoauth/mcoauth.py
mcoauth_MySixSenses-0.0.1.dist-info/LICENSE
mcoauth_MySixSenses-0.0.1.dist-info/METADATA
mcoauth_MySixSenses-0.0.1.dist-info/WHEEL
mcoauth_MySixSenses-0.0.1.dist-info/top_level.txt
mcoauth_MySixSenses-0.0.1.dist-info/RECORD
